memelib/__init__.py
memelib/_utils.py
memelib/api.py
memelib/errors.py
MemeLib-0.1.5.dist-info/LICENSE
MemeLib-0.1.5.dist-info/METADATA
MemeLib-0.1.5.dist-info/WHEEL
MemeLib-0.1.5.dist-info/top_level.txt
MemeLib-0.1.5.dist-info/RECORD
