Metadata-Version: 2.1
Name: MemeLib
Version: 0.1.5
Summary: A python lib to get dank memes
Home-page: https://github.com/CraziiAce/MemeLib
Author: CraziiAce
Author-email: teddyjraz@gmail.com
License: UNKNOWN
Platform: UNKNOWN
Classifier: Programming Language :: Python :: 3
Classifier: License :: OSI Approved :: GNU General Public License v3 (GPLv3)
Classifier: Operating System :: OS Independent
Requires-Python: >=3.6
Requires-Dist: aiohttp
Requires-Dist: discord
Requires-Dist: requests
